LICENSE
README.md
setup.cfg
setup.py
open_publishing/__init__.py
open_publishing/account.py
open_publishing/archive.py
open_publishing/assets.py
open_publishing/audience.py
open_publishing/audio.py
open_publishing/bisac.py
open_publishing/brands.py
open_publishing/content.py
open_publishing/country.py
open_publishing/currency.py
open_publishing/dates.py
open_publishing/distribution_availability.py
open_publishing/distribution_channels.py
open_publishing/document.py
open_publishing/document_list.py
open_publishing/extendable_enum_field.py
open_publishing/files.py
open_publishing/genre.py
open_publishing/imprint.py
open_publishing/isbns.py
open_publishing/labels.py
open_publishing/misc.py
open_publishing/object_events.py
open_publishing/order.py
open_publishing/order_fulfillment.py
open_publishing/publications.py
open_publishing/search_tags.py
open_publishing/subscriptions.py
open_publishing/user.py
open_publishing.egg-info/PKG-INFO
open_publishing.egg-info/SOURCES.txt
open_publishing.egg-info/dependency_links.txt
open_publishing.egg-info/not-zip-safe
open_publishing.egg-info/requires.txt
open_publishing.egg-info/top_level.txt
open_publishing/authors/__init__.py
open_publishing/authors/authors_list.py
open_publishing/authors/document_author.py
open_publishing/catalog/__init__.py
open_publishing/catalog/catalog_field.py
open_publishing/catalog/catalog_types.py
open_publishing/catalog/institution.py
open_publishing/catalog/public.py
open_publishing/catalog/series.py
open_publishing/catalog/subject.py
open_publishing/catalog/thema.py
open_publishing/context/__init__.py
open_publishing/context/accounts.py
open_publishing/context/assets.py
open_publishing/context/bisac_subjects.py
open_publishing/context/context.py
open_publishing/context/countries.py
open_publishing/context/documents.py
open_publishing/context/events.py
open_publishing/context/genres.py
open_publishing/context/imprints.py
open_publishing/context/isbns.py
open_publishing/context/me.py
open_publishing/context/onix.py
open_publishing/context/order_fulfillments.py
open_publishing/context/orders.py
open_publishing/context/testdata.py
open_publishing/context/users.py
open_publishing/core/__init__.py
