Metadata-Version: 2.1
Name: open-publishing
Version: 0.0.17
Summary: API Wrapper for Open Publishing API
Home-page: https://api.openpublishing.com/
Author: Open Publishing GmbH
Author-email: info@openpublishing.com
License: Open Publishing License
Download-URL: https://github.com/open-publishing/open-publishing-api/archive/0.0.17.zip
Keywords: publishing book ebook
Platform: UNKNOWN
Classifier: Development Status :: 3 - Alpha
Classifier: Intended Audience :: End Users/Desktop
Classifier: Intended Audience :: Developers
Classifier: Programming Language :: Python :: 3.5
Classifier: Programming Language :: Python :: 3.6
License-File: LICENSE
